mnemonic_major_encoder/__init__.py
mnemonic_major_encoder/decoder.py
mnemonic_major_encoder/encoder.py
mnemonic_major_encoder/dictionaries/italungo-encoded.txt
mnemonic_major_encoder/dictionaries/italungo.txt
mnemonic_major_encoder-0.1.7.dist-info/AUTHORS.rst
mnemonic_major_encoder-0.1.7.dist-info/LICENSE
mnemonic_major_encoder-0.1.7.dist-info/METADATA
mnemonic_major_encoder-0.1.7.dist-info/WHEEL
mnemonic_major_encoder-0.1.7.dist-info/top_level.txt
mnemonic_major_encoder-0.1.7.dist-info/RECORD
