Metadata-Version: 2.1
Name: mnemonic-major-encoder
Version: 0.1.7
Summary: Encode and Decode text by the Major System
Home-page: https://github.com/JackNova/mnemonic_major_encoder
Author: Dario Iacampo
Author-email: dario@jntstudio.net
License: MIT license
Keywords: mnemonic_major_encoder
Platform: UNKNOWN
Classifier: Development Status :: 2 - Pre-Alpha
Classifier: Intended Audience :: Developers
Classifier: License :: OSI Approved :: MIT License
Classifier: Natural Language :: English
Classifier: Programming Language :: Python :: 2
Classifier: Programming Language :: Python :: 3
Classifier: Programming Language :: Python :: 3.4
Classifier: Programming Language :: Python :: 3.5
Classifier: Programming Language :: Python :: 3.6
Classifier: Programming Language :: Python :: 3.7
Requires-Dist: unidecode
